consolectrlchandler/README.MD
consolectrlchandler/__init__.py
consolectrlchandler/requirements.txt
consolectrlchandler/thirdparty.json
consolectrlchandler-0.11.dist-info/LICENSE.rst
consolectrlchandler-0.11.dist-info/METADATA
consolectrlchandler-0.11.dist-info/WHEEL
consolectrlchandler-0.11.dist-info/top_level.txt
consolectrlchandler-0.11.dist-info/RECORD
