Metadata-Version: 2.1
Name: consolectrlchandler
Version: 0.11
Summary: Handler for CTRL_C_EVENT, CTRL_BREAK_EVENT, CTRL_CLOSE_EVENT, CTRL_LOGOFF_EVENT, CTRL_SHUTDOWN_EVENT
Home-page: https://github.com/hansalemaos/consolectrlchandler
Author: Johannes Fischer
Author-email: aulasparticularesdealemaosp@gmail.com
License: MIT
Keywords: ctrl,handler,break
Classifier: Development Status :: 4 - Beta
Classifier: Programming Language :: Python :: 3 :: Only
Classifier: Programming Language :: Python :: 3.10
Classifier: Topic :: Software Development :: Libraries :: Python Modules
Classifier: Topic :: Utilities
License-File: LICENSE.rst
